pytest_mongodb/__init__.py
pytest_mongodb/plugin.py
pytest_mongodb-2.4.0.dist-info/METADATA
pytest_mongodb-2.4.0.dist-info/WHEEL
pytest_mongodb-2.4.0.dist-info/entry_points.txt
pytest_mongodb-2.4.0.dist-info/top_level.txt
pytest_mongodb-2.4.0.dist-info/RECORD
