Metadata-Version: 2.1
Name: pytest-mongodb
Version: 2.4.0
Summary: pytest plugin for MongoDB fixtures
Author-email: Martin Domke <mail@martindomke.net>
License: MIT
Project-URL: homepage, https://github.com/mdomke/pytest-mongodb
Classifier: Development Status :: 5 - Production/Stable
Classifier: Environment :: Console
Classifier: Intended Audience :: Developers
Classifier: License :: OSI Approved :: MIT License
Classifier: Operating System :: POSIX :: Linux
Classifier: Operating System :: MacOS :: MacOS X
Classifier: Programming Language :: Python
Classifier: Programming Language :: Python :: 3
Classifier: Framework :: Pytest
Classifier: Topic :: Database
Classifier: Topic :: Software Development :: Libraries
